{"cameraMode":{"drawMode":0,"name":"Shaded","section":"Shading Mode"},"sceneLighting":true,"audioPlay":false,"sceneViewState":{"m_AlwaysRefresh":false,"showFog":true,"showSkybox":true,"showFlares":true,"showImageEffects":true,"showParticleSystems":true,"showVisualEffectGraphs":true,"m_FxEnabled":true},"in2DMode":false,"pivot":{"x":-9.677799224853516,"y":3.749149799346924,"z":-6.0715718269348148},"rotation":{"x":0.03431668505072594,"y":-0.667857825756073,"z":-0.030893491581082345,"w":-0.7428759932518005},"size":3.389500141143799,"orthographic":false}